derivslib/__init__.py
derivslib/data/__init__.py
derivslib/examples/__init__.py
derivslib/src/__init__.py
derivslib/src/derivslib.py
derivslib/src/market.py
derivslib/src/utils.py
derivslib-0.0.16.dist-info/METADATA
derivslib-0.0.16.dist-info/WHEEL
derivslib-0.0.16.dist-info/top_level.txt
derivslib-0.0.16.dist-info/RECORD
