Metadata-Version: 2.1
Name: derivslib
Version: 0.0.16
Summary: Provides pricing tools and data for various derivative assets. I am not an attorney, accountant or financial advisor, nor am I holding myself out to be, and the information and tools contained in this package is not a substitute for financial advice from a professional who is aware of the facts and circumstances of your individual situation.
Home-page: https://github.com/lwarner100/derivslib
Author: UNKNOWN
Author-email: UNKNOWN
License: MIT
Platform: UNKNOWN
Classifier: Intended Audience :: Developers
Classifier: License :: OSI Approved :: MIT License
Classifier: Programming Language :: Python :: 3
Classifier: Programming Language :: Python :: 3.7
Classifier: Programming Language :: Python :: 3.8
Classifier: Programming Language :: Python :: 3.9
Classifier: Programming Language :: Python :: 3.10
Classifier: Programming Language :: Python :: 3.11
Requires-Dist: ipywidgets
Requires-Dist: matplotlib
Requires-Dist: numpy
Requires-Dist: pandas
Requires-Dist: plotly
Requires-Dist: scipy
Requires-Dist: seaborn
